{
  "version": "5.2.1",
  "flags": {},
  "shapes": [
    {
      "label": "big robot",
      "points": [
        [
          974.7727272727273,
          874.0909090909091
        ],
        [
          1447.4999999999998,
          1335.4545454545455
        ]
      ],
      "group_id": null,
      "description": "",
      "shape_type": "rectangle",
      "flags": {}
    },
    {
      "label": "small robot",
      "points": [
        [
          1574.7727272727273,
          958.1818181818182
        ],
        [
          1840.681818181818,
          1276.3636363636365
        ]
      ],
      "group_id": null,
      "description": "",
      "shape_type": "rectangle",
      "flags": {}
    },
    {
      "label": "big robot",
      "points": [
        [
          1933.8636363636363,
          858.1818181818182
        ],
        [
          2333.863636363636,
          1221.818181818182
        ]
      ],
      "group_id": null,
      "description": "",
      "shape_type": "rectangle",
      "flags": {}
    }
  ],
  "imagePath": "IMG_7651.JPG",
  "imageData": null,
  "imageHeight": 1980,
  "imageWidth": 3520
}